MIS_algorithms/__init__.py
MIS_algorithms/blelloch.py
MIS_algorithms/continuation.py
MIS_algorithms/exact.py
MIS_algorithms/greedy.py
MIS_algorithms/lotkavolterra.py
MIS_algorithms/luby.py
MIS_algorithms/random_priority_parallel.py
MIS_algorithms/functions/__init__.py
MIS_algorithms/functions/is_maximal_independent_set.py
MIS_algorithms/functions/reduced_graph.py
MIS_algorithms/generate_graphs/__init__.py
MIS_algorithms/generate_graphs/barabasi_albert.py
MIS_algorithms/generate_graphs/erdos_renyi.py
MIS_algorithms/generate_graphs/random_bipartite.py
MIS_algorithms/generate_graphs/random_geometric.py
MIS_algorithms-1.1.1.dist-info/LICENSE.txt
MIS_algorithms-1.1.1.dist-info/METADATA
MIS_algorithms-1.1.1.dist-info/WHEEL
MIS_algorithms-1.1.1.dist-info/entry_points.txt
MIS_algorithms-1.1.1.dist-info/top_level.txt
MIS_algorithms-1.1.1.dist-info/RECORD
